<?xml version="1.0" encoding="utf-8" ?>
<Defs>

 <WorkGiverDef>
    <defName>RB_InsertDroneInBeehouse</defName>
    <label>inserting drone in beehouse</label>
    <giverClass>RimBees.WorkGiver_InsertDroneInBeehouse</giverClass>
    <workType>RB_BeekeepingWork</workType>
    <verb>insert drone in beehouse</verb>
    <gerund>inserting drone in beehouse</gerund>
    <priorityInType>20</priorityInType>
    <requiredCapacities>
      <li>Manipulation</li>
    </requiredCapacities>
  </WorkGiverDef>
  
   <WorkGiverDef>
    <defName>RB_InsertQueenInBeehouse</defName>
    <label>inserting queen in beehouse</label>
    <giverClass>RimBees.WorkGiver_InsertQueenInBeehouse</giverClass>
    <workType>RB_BeekeepingWork</workType>
    <verb>insert queen in beehouse</verb>
    <gerund>inserting queen in beehouse</gerund>
    <priorityInType>21</priorityInType>
    <requiredCapacities>
      <li>Manipulation</li>
    </requiredCapacities>
  </WorkGiverDef>
  
 

	<WorkGiverDef>
		<defName>RB_DoBillsHoneyCentrifuge</defName>
		<label>works at honey centrifuge</label>
		<giverClass>WorkGiver_DoBill</giverClass>
		<workType>RB_BeekeepingWork</workType>
		<priorityInType>100</priorityInType>
		<fixedBillGiverDefs>
			<li>RB_Honey_Centrifuge</li>
		</fixedBillGiverDefs>
		<verb>extracting honey and wax</verb>
		<gerund>extracting honey and wax at</gerund>
		<requiredCapacities>
			<li>Manipulation</li>
		</requiredCapacities>
		<prioritizeSustains>true</prioritizeSustains>
	</WorkGiverDef>
	
	<WorkGiverDef>
		<defName>RB_DoBillsBeeResearchTable</defName>
		<label>works at bee research table</label>
		<giverClass>WorkGiver_DoBill</giverClass>
		<workType>RB_BeekeepingWork</workType>
		<priorityInType>100</priorityInType>
		<fixedBillGiverDefs>
			<li>RB_BeeResearchTable</li>
		</fixedBillGiverDefs>
		<verb>work at bee research table</verb>
		<gerund>working at bee research table</gerund>
		<requiredCapacities>
			<li>Manipulation</li>
		</requiredCapacities>
		<prioritizeSustains>true</prioritizeSustains>
	</WorkGiverDef>
	
	<WorkGiverDef>
		<defName>RB_DoBillsAdvancedHoneyCentrifuge</defName>
		<label>works at advanced honey centrifuge</label>
		<giverClass>WorkGiver_DoBill</giverClass>
		<workType>RB_BeekeepingWork</workType>
		<priorityInType>100</priorityInType>
		<fixedBillGiverDefs>
			<li>RB_Advanced_Honey_Centrifuge</li>
		</fixedBillGiverDefs>
		<verb>bulk extracting honey and wax</verb>
		<gerund>bulk extracting honey and wax at</gerund>
		<requiredCapacities>
			<li>Manipulation</li>
		</requiredCapacities>
		<prioritizeSustains>true</prioritizeSustains>
	</WorkGiverDef>
	
	<WorkGiverDef>
		<defName>RB_DoBillsBeekeepingWorkbench</defName>
		
		<label>works at beekeeping workbench</label>
		<giverClass>WorkGiver_DoBill</giverClass>
		<workType>RB_BeekeepingWork</workType>
		<priorityInType>100</priorityInType>
		<fixedBillGiverDefs>
			<li>RB_Beekeeping_Workbench_Building</li>
		</fixedBillGiverDefs>
		<verb>working</verb>
		<gerund>working at</gerund>
		<requiredCapacities>
			<li>Manipulation</li>
		</requiredCapacities>
		<prioritizeSustains>true</prioritizeSustains>
	</WorkGiverDef>
	
<WorkGiverDef>
    <defName>RB_TakeThingsOutOfBeehouse</defName>
    <label>taking things out of beehouse</label>
    <giverClass>RimBees.WorkGiver_TakeThingsOutOfBeehouse</giverClass>
    <workType>RB_BeekeepingWork</workType>
    <verb>take things out of beehouse</verb>
    <gerund>taking things out of beehouse</gerund>
    <priorityInType>10</priorityInType>
    <requiredCapacities>
      <li>Manipulation</li>
    </requiredCapacities>
  </WorkGiverDef>
  
 
  
  <WorkGiverDef>
    <defName>RB_TakeThingsOutOfBroodChamber</defName>
    <label>taking bees out of brood chamber</label>
    <giverClass>RimBees.WorkGiver_TakeThingsOutOfBroodChamber</giverClass>
    <workType>RB_BeekeepingWork</workType>
    <verb>take bees out of brood chamber</verb>
    <gerund>taking bees out of brood chamber</gerund>
    <priorityInType>13</priorityInType>
    <requiredCapacities>
      <li>Manipulation</li>
    </requiredCapacities>
  </WorkGiverDef> 
    
  <WorkGiverDef>
    <defName>RB_TakeThingsOutOfHybridizationChamber</defName>
    <label>taking bees out of hybridization chamber</label>
    <giverClass>RimBees.WorkGiver_TakeThingsOutOfHybridizationChamber</giverClass>
    <workType>RB_BeekeepingWork</workType>
    <verb>take bees out of hybridization chamber</verb>
    <gerund>taking bees out of hybridization chamber</gerund>
    <priorityInType>14</priorityInType>
    <requiredCapacities>
      <li>Manipulation</li>
    </requiredCapacities>
  </WorkGiverDef>
	
	<WorkGiverDef>
    <defName>RB_TakeBeerOutOfFermentingBarrel</defName>
    <label>take mead out of fermenting barrels</label>
    <giverClass>RimBees.WorkGiver_TakeMeadOutOfFermentingBarrel</giverClass>
    <workType>Hauling</workType>
    <verb>take mead</verb>
    <gerund>taking mead from</gerund>
    <priorityInType>20</priorityInType>
    <requiredCapacities>
      <li>Manipulation</li>
    </requiredCapacities>
  </WorkGiverDef>
  
  <WorkGiverDef>
    <defName>RB_FillMeadFermentingBarrel</defName>
    <label>fill fermenting barrels</label>
    <giverClass>RimBees.WorkGiver_FillMeadFermentingBarrel</giverClass>
    <workType>Hauling</workType>
    <verb>fill</verb>
    <gerund>filling</gerund>
    <priorityInType>19</priorityInType>
    <requiredCapacities>
      <li>Manipulation</li>
    </requiredCapacities>
  </WorkGiverDef>
	
	



</Defs>